msteams_con/__init__.py
msteams_con/adaptive_card.py
msteams_con/cli.py
msteams_con/errors.py
msteams_con/logger.py
msteams_con/msteams_connector.py
msteams_con/requirements-dev.txt
msteams_con/requirements.txt
msteams_con/card_templates/__init__.py
msteams_con/card_templates/release_card.py
msteams_con-1.0.1.dist-info/LICENSE
msteams_con-1.0.1.dist-info/METADATA
msteams_con-1.0.1.dist-info/WHEEL
msteams_con-1.0.1.dist-info/entry_points.txt
msteams_con-1.0.1.dist-info/top_level.txt
msteams_con-1.0.1.dist-info/RECORD
