Metadata-Version: 2.1
Name: msteams_con
Version: 1.0.1
Summary: msteams-connector is a Python-based tool to simplify the process of sending messages, adaptive card to Microsoft Teams channels via  incoming webhooks. Whether you’re automating release notifications, error alerts, or general messages, this connector provides a seamless interface for working with Microsoft Teams.
Author-email: Nguyen Tri Man <ntman.ute@gmail.com>
License: Mozilla Public License Version 2.0
Project-URL: Changelog, https://github.com/cloud-bees/msteams-connector/blob/main/CHANGELOG.md
Project-URL: Repository, https://github.com/cloud-bees/msteams-connector
Project-URL: Documentation, https://github.com/cloud-bees/msteams-connector/blob/main/README.md
Project-URL: Homepage, https://github.com/cloud-bees/msteams-connector
Project-URL: Download, https://pypi.org/project/Sphinx/
Project-URL: Issue tracker, https://github.com/cloud-bees/msteams-connector/issues
Classifier: Development Status :: 4 - Beta
Classifier: Programming Language :: Python
Classifier: Programming Language :: Python :: 3 :: Only
Classifier: Programming Language :: Python :: 3.10
Classifier: Programming Language :: Python :: 3.11
Requires-Python: >=3.10
License-File: LICENSE
Requires-Dist: fire ==0.7.0
Requires-Dist: requests ==2.32.3
Provides-Extra: dev
Requires-Dist: fire ==0.7.0 ; extra == 'dev'
Requires-Dist: requests ==2.32.3 ; extra == 'dev'
Requires-Dist: pytest ==8.3.3 ; extra == 'dev'
Requires-Dist: pytest-cov ==5.0.0 ; extra == 'dev'
Requires-Dist: ruff ==0.6.8 ; extra == 'dev'
